setup.py
TheBatman.egg-info/PKG-INFO
TheBatman.egg-info/SOURCES.txt
TheBatman.egg-info/dependency_links.txt
TheBatman.egg-info/not-zip-safe
TheBatman.egg-info/top_level.txt
src/__init__.py
src/tools.py