Metadata-Version: 2.1
Name: TheBatman
Version: 0.0.1
Summary: Some handy tools
Home-page: UNKNOWN
Author: Harish PVV
Author-email: harishpvv@gmail.com
License: MIT
Keywords: harishpvv
Platform: UNKNOWN
Classifier: Programming Language :: Python :: 3
Classifier: License :: OSI Approved :: MIT License
Classifier: Operating System :: OS Independent
